scott/__init__.py
scott/compare.py
scott/kilt.py
scott/geometry/__init__.py
scott/geometry/measures/__init__.py
scott/geometry/measures/forman.py
scott/geometry/measures/ollivier.py
scott/geometry/measures/resistance.py
scott/topology/__init__.py
scott/topology/ph.py
scott/topology/distances/__init__.py
scott/topology/distances/base.py
scott/topology/distances/image.py
scott/topology/distances/landscape.py
scott/topology/representations/__init__.py
scott/topology/representations/diagram.py
scott/topology/representations/image.py
scott/topology/representations/landscape.py
curvature_filtrations-0.1.2.dist-info/METADATA
curvature_filtrations-0.1.2.dist-info/WHEEL
curvature_filtrations-0.1.2.dist-info/licenses/LICENSE
curvature_filtrations-0.1.2.dist-info/RECORD
