Metadata-Version: 2.4
Name: curvature-filtrations
Version: 0.1.2
Summary: SCOTT: Synthesizing Curvature Operations and Topology Tools. Use curvature filtrations for graphs and graph distributions!
Author-email: Jeremy Wayland <jeremy.don.wayland@gmail.com>, Emily Simons <emsimons4@gmail.com>, Bastian Rieck <bastian@rieck.me>
License: BSD 3-Clause License
License-File: LICENSE
Requires-Python: >=3.10
Requires-Dist: gudhi>=3.11.0
Requires-Dist: joblib>=1.5.2
Requires-Dist: networkx>=3.4.2
Requires-Dist: pot>=0.9.5
Requires-Dist: scikit-learn>=1.5.2
Provides-Extra: dev
Requires-Dist: black>=25.9.0; extra == 'dev'
Requires-Dist: pytest>=8.3.3; extra == 'dev'
Provides-Extra: docs
Requires-Dist: furo>=2024.8.6; extra == 'docs'
